{"cameraMode":{"drawMode":0,"name":"Shaded","section":"Shading Mode"},"sceneLighting":true,"audioPlay":false,"sceneViewState":{"m_AlwaysRefresh":false,"showFog":true,"showSkybox":true,"showFlares":true,"showImageEffects":true,"showParticleSystems":true,"showVisualEffectGraphs":true,"m_FxEnabled":true},"in2DMode":false,"pivot":{"x":0.09014403820037842,"y":0.0067794593051075939,"z":0.3901239335536957},"rotation":{"x":0.07823122292757034,"y":-0.008014274761080742,"z":0.000986265018582344,"w":0.9971268773078919},"size":0.040575698018074039,"orthographic":false}